{
  "palettes": {
    "primary": {
      "0": {
        "value": "{palettes.primary.500}",
        "type": "color",
        "$extensions": {
          "studio.tokens": {
            "modify": {
              "type": "lighten",
              "value": "1",
              "space": "hsl"
            }
          }
        }
      },
      "50": {
        "value": "{palettes.primary.500}",
        "type": "color",
        "$extensions": {
          "studio.tokens": {
            "modify": {
              "type": "lighten",
              "value": "0.9",
              "space": "hsl"
            }
          }
        }
      },
      "100": {
        "value": "{palettes.primary.500}",
        "type": "color",
        "$extensions": {
          "studio.tokens": {
            "modify": {
              "type": "lighten",
              "value": "0.8",
              "space": "hsl"
            }
          }
        }
      },
      "200": {
        "value": "{palettes.primary.500}",
        "type": "color",
        "$extensions": {
          "studio.tokens": {
            "modify": {
              "type": "lighten",
              "value": "0.6",
              "space": "hsl"
            }
          }
        }
      },
      "300": {
        "value": "{palettes.primary.500}",
        "type": "color",
        "$extensions": {
          "studio.tokens": {
            "modify": {
              "type": "lighten",
              "value": "0.4",
              "space": "hsl"
            }
          }
        }
      },
      "400": {
        "value": "{palettes.primary.500}",
        "type": "color",
        "$extensions": {
          "studio.tokens": {
            "modify": {
              "type": "lighten",
              "value": "0.2",
              "space": "hsl"
            }
          }
        }
      },
      "500": {
        "value": "{key-colors.primary}",
        "type": "color",
        "description": "This is manually adjusted to match hsl with l = 50%",
        "$extensions": {
          "studio.tokens": {
            "modify": {
              "type": "lighten",
              "value": "0.166",
              "space": "hsl"
            }
          }
        }
      },
      "600": {
        "value": "{palettes.primary.500}",
        "type": "color",
        "$extensions": {
          "studio.tokens": {
            "modify": {
              "type": "darken",
              "value": "0.2",
              "space": "hsl"
            }
          }
        }
      },
      "700": {
        "value": "{palettes.primary.500}",
        "type": "color",
        "$extensions": {
          "studio.tokens": {
            "modify": {
              "type": "darken",
              "value": "0.4",
              "space": "hsl"
            }
          }
        }
      },
      "800": {
        "value": "{palettes.primary.500}",
        "type": "color",
        "$extensions": {
          "studio.tokens": {
            "modify": {
              "type": "darken",
              "value": "0.6",
              "space": "hsl"
            }
          }
        }
      },
      "900": {
        "value": "{palettes.primary.500}",
        "type": "color",
        "$extensions": {
          "studio.tokens": {
            "modify": {
              "type": "darken",
              "value": "0.8",
              "space": "hsl"
            }
          }
        }
      },
      "1000": {
        "value": "{palettes.primary.500}",
        "type": "color",
        "$extensions": {
          "studio.tokens": {
            "modify": {
              "type": "darken",
              "value": "1",
              "space": "hsl"
            }
          }
        }
      },
      "test": {
        "value": "{key-colors.primary}",
        "type": "color",
        "description": "49 L is the ideal (based on an expert in color from facebook - Ashley Seto - Lead Product Designer, Meta",
        "$extensions": {
          "studio.tokens": {
            "modify": {
              "type": "darken",
              "value": ".185",
              "space": "lch"
            }
          }
        }
      }
    },
    "secondary": {
      "0": {
        "value": "{palettes.secondary.500}",
        "type": "color",
        "$extensions": {
          "studio.tokens": {
            "modify": {
              "type": "lighten",
              "value": "1",
              "space": "hsl"
            }
          }
        }
      },
      "50": {
        "value": "{palettes.secondary.500}",
        "type": "color",
        "$extensions": {
          "studio.tokens": {
            "modify": {
              "type": "lighten",
              "value": "0.9",
              "space": "hsl"
            }
          }
        }
      },
      "100": {
        "value": "{palettes.secondary.500}",
        "type": "color",
        "$extensions": {
          "studio.tokens": {
            "modify": {
              "type": "lighten",
              "value": "0.8",
              "space": "hsl"
            }
          }
        }
      },
      "200": {
        "value": "{palettes.secondary.500}",
        "type": "color",
        "$extensions": {
          "studio.tokens": {
            "modify": {
              "type": "lighten",
              "value": "0.6",
              "space": "hsl"
            }
          }
        }
      },
      "300": {
        "value": "{palettes.secondary.500}",
        "type": "color",
        "$extensions": {
          "studio.tokens": {
            "modify": {
              "type": "lighten",
              "value": "0.4",
              "space": "hsl"
            }
          }
        }
      },
      "400": {
        "value": "{palettes.secondary.500}",
        "type": "color",
        "$extensions": {
          "studio.tokens": {
            "modify": {
              "type": "lighten",
              "value": "0.2",
              "space": "hsl"
            }
          }
        }
      },
      "500": {
        "value": "{key-colors.secondary}",
        "type": "color",
        "description": "This is manually adjusted to match hsl with l = 50%",
        "$extensions": {
          "studio.tokens": {
            "modify": {
              "type": "lighten",
              "value": "0.166",
              "space": "hsl"
            }
          }
        }
      },
      "600": {
        "value": "{palettes.secondary.500}",
        "type": "color",
        "$extensions": {
          "studio.tokens": {
            "modify": {
              "type": "darken",
              "value": "0.2",
              "space": "hsl"
            }
          }
        }
      },
      "700": {
        "value": "{palettes.secondary.500}",
        "type": "color",
        "$extensions": {
          "studio.tokens": {
            "modify": {
              "type": "darken",
              "value": "0.4",
              "space": "hsl"
            }
          }
        }
      },
      "800": {
        "value": "{palettes.secondary.500}",
        "type": "color",
        "$extensions": {
          "studio.tokens": {
            "modify": {
              "type": "darken",
              "value": "0.6",
              "space": "hsl"
            }
          }
        }
      },
      "900": {
        "value": "{palettes.secondary.500}",
        "type": "color",
        "$extensions": {
          "studio.tokens": {
            "modify": {
              "type": "darken",
              "value": "0.8",
              "space": "hsl"
            }
          }
        }
      },
      "1000": {
        "value": "{palettes.secondary.500}",
        "type": "color",
        "$extensions": {
          "studio.tokens": {
            "modify": {
              "type": "darken",
              "value": "1",
              "space": "hsl"
            }
          }
        }
      }
    },
    "tertiary": {
      "0": {
        "value": "{palettes.tertiary.500}",
        "type": "color",
        "$extensions": {
          "studio.tokens": {
            "modify": {
              "type": "lighten",
              "value": "1",
              "space": "hsl"
            }
          }
        }
      },
      "50": {
        "value": "{palettes.tertiary.500}",
        "type": "color",
        "$extensions": {
          "studio.tokens": {
            "modify": {
              "type": "lighten",
              "value": "0.9",
              "space": "hsl"
            }
          }
        }
      },
      "100": {
        "value": "{palettes.tertiary.500}",
        "type": "color",
        "$extensions": {
          "studio.tokens": {
            "modify": {
              "type": "lighten",
              "value": "0.8",
              "space": "hsl"
            }
          }
        }
      },
      "200": {
        "value": "{palettes.tertiary.500}",
        "type": "color",
        "$extensions": {
          "studio.tokens": {
            "modify": {
              "type": "lighten",
              "value": "0.6",
              "space": "hsl"
            }
          }
        }
      },
      "300": {
        "value": "{palettes.tertiary.500}",
        "type": "color",
        "$extensions": {
          "studio.tokens": {
            "modify": {
              "type": "lighten",
              "value": "0.4",
              "space": "hsl"
            }
          }
        }
      },
      "400": {
        "value": "{palettes.tertiary.500}",
        "type": "color",
        "$extensions": {
          "studio.tokens": {
            "modify": {
              "type": "lighten",
              "value": "0.2",
              "space": "hsl"
            }
          }
        }
      },
      "500": {
        "value": "{key-colors.tertiary}",
        "type": "color",
        "description": "This is manually adjusted to match hsl with l = 50%",
        "$extensions": {
          "studio.tokens": {
            "modify": {
              "type": "darken",
              "value": "0.2815",
              "space": "hsl"
            }
          }
        }
      },
      "600": {
        "value": "{palettes.tertiary.500}",
        "type": "color",
        "$extensions": {
          "studio.tokens": {
            "modify": {
              "type": "darken",
              "value": "0.2",
              "space": "hsl"
            }
          }
        }
      },
      "700": {
        "value": "{palettes.tertiary.500}",
        "type": "color",
        "$extensions": {
          "studio.tokens": {
            "modify": {
              "type": "darken",
              "value": "0.4",
              "space": "hsl"
            }
          }
        }
      },
      "800": {
        "value": "{palettes.tertiary.500}",
        "type": "color",
        "$extensions": {
          "studio.tokens": {
            "modify": {
              "type": "darken",
              "value": "0.6",
              "space": "hsl"
            }
          }
        }
      },
      "900": {
        "value": "{palettes.tertiary.500}",
        "type": "color",
        "$extensions": {
          "studio.tokens": {
            "modify": {
              "type": "darken",
              "value": "0.8",
              "space": "hsl"
            }
          }
        }
      },
      "1000": {
        "value": "{palettes.tertiary.500}",
        "type": "color",
        "$extensions": {
          "studio.tokens": {
            "modify": {
              "type": "darken",
              "value": "1",
              "space": "hsl"
            }
          }
        }
      }
    },
    "error": {
      "0": {
        "value": "{palettes.error.500}",
        "type": "color",
        "$extensions": {
          "studio.tokens": {
            "modify": {
              "type": "lighten",
              "value": "1",
              "space": "hsl"
            }
          }
        }
      },
      "50": {
        "value": "{palettes.error.500}",
        "type": "color",
        "$extensions": {
          "studio.tokens": {
            "modify": {
              "type": "lighten",
              "value": "0.9",
              "space": "hsl"
            }
          }
        }
      },
      "100": {
        "value": "{palettes.error.500}",
        "type": "color",
        "$extensions": {
          "studio.tokens": {
            "modify": {
              "type": "lighten",
              "value": "0.8",
              "space": "hsl"
            }
          }
        }
      },
      "200": {
        "value": "{palettes.error.500}",
        "type": "color",
        "$extensions": {
          "studio.tokens": {
            "modify": {
              "type": "lighten",
              "value": "0.6",
              "space": "hsl"
            }
          }
        }
      },
      "300": {
        "value": "{palettes.error.500}",
        "type": "color",
        "$extensions": {
          "studio.tokens": {
            "modify": {
              "type": "lighten",
              "value": "0.4",
              "space": "hsl"
            }
          }
        }
      },
      "400": {
        "value": "{palettes.error.500}",
        "type": "color",
        "$extensions": {
          "studio.tokens": {
            "modify": {
              "type": "lighten",
              "value": "0.2",
              "space": "hsl"
            }
          }
        }
      },
      "500": {
        "value": "{key-colors.error}",
        "type": "color",
        "description": "This is manually adjusted to match hsl with l = 50%",
        "$extensions": {
          "studio.tokens": {
            "modify": {
              "type": "darken",
              "value": "0.105",
              "space": "hsl"
            }
          }
        }
      },
      "600": {
        "value": "{palettes.error.500}",
        "type": "color",
        "$extensions": {
          "studio.tokens": {
            "modify": {
              "type": "darken",
              "value": "0.2",
              "space": "hsl"
            }
          }
        }
      },
      "700": {
        "value": "{palettes.error.500}",
        "type": "color",
        "$extensions": {
          "studio.tokens": {
            "modify": {
              "type": "darken",
              "value": "0.4",
              "space": "hsl"
            }
          }
        }
      },
      "800": {
        "value": "{palettes.error.500}",
        "type": "color",
        "$extensions": {
          "studio.tokens": {
            "modify": {
              "type": "darken",
              "value": "0.6",
              "space": "hsl"
            }
          }
        }
      },
      "900": {
        "value": "{palettes.error.500}",
        "type": "color",
        "$extensions": {
          "studio.tokens": {
            "modify": {
              "type": "darken",
              "value": "0.8",
              "space": "hsl"
            }
          }
        }
      },
      "1000": {
        "value": "{palettes.error.500}",
        "type": "color",
        "$extensions": {
          "studio.tokens": {
            "modify": {
              "type": "darken",
              "value": "1",
              "space": "hsl"
            }
          }
        }
      }
    },
    "neutral": {
      "0": {
        "value": "{palettes.neutral.500}",
        "type": "color",
        "$extensions": {
          "studio.tokens": {
            "modify": {
              "type": "lighten",
              "value": "1",
              "space": "hsl"
            }
          }
        }
      },
      "50": {
        "value": "{palettes.neutral.500}",
        "type": "color",
        "$extensions": {
          "studio.tokens": {
            "modify": {
              "type": "lighten",
              "value": "0.9",
              "space": "hsl"
            }
          }
        }
      },
      "100": {
        "value": "{palettes.neutral.500}",
        "type": "color",
        "$extensions": {
          "studio.tokens": {
            "modify": {
              "type": "lighten",
              "value": "0.8",
              "space": "hsl"
            }
          }
        }
      },
      "200": {
        "value": "{palettes.neutral.500}",
        "type": "color",
        "$extensions": {
          "studio.tokens": {
            "modify": {
              "type": "lighten",
              "value": "0.6",
              "space": "hsl"
            }
          }
        }
      },
      "300": {
        "value": "{palettes.neutral.500}",
        "type": "color",
        "$extensions": {
          "studio.tokens": {
            "modify": {
              "type": "lighten",
              "value": "0.4",
              "space": "hsl"
            }
          }
        }
      },
      "400": {
        "value": "{palettes.neutral.500}",
        "type": "color",
        "$extensions": {
          "studio.tokens": {
            "modify": {
              "type": "lighten",
              "value": "0.2",
              "space": "hsl"
            }
          }
        }
      },
      "500": {
        "value": "{key-colors.neutral}",
        "type": "color",
        "description": "This is manually adjusted to match hsl with l = 50%",
        "$extensions": {
          "studio.tokens": {
            "modify": {
              "type": "darken",
              "value": "0.48",
              "space": "hsl"
            }
          }
        }
      },
      "600": {
        "value": "{palettes.neutral.500}",
        "type": "color",
        "$extensions": {
          "studio.tokens": {
            "modify": {
              "type": "darken",
              "value": "0.2",
              "space": "hsl"
            }
          }
        }
      },
      "700": {
        "value": "{palettes.neutral.500}",
        "type": "color",
        "$extensions": {
          "studio.tokens": {
            "modify": {
              "type": "darken",
              "value": "0.4",
              "space": "hsl"
            }
          }
        }
      },
      "800": {
        "value": "{palettes.neutral.500}",
        "type": "color",
        "$extensions": {
          "studio.tokens": {
            "modify": {
              "type": "darken",
              "value": "0.6",
              "space": "hsl"
            }
          }
        }
      },
      "900": {
        "value": "{palettes.neutral.500}",
        "type": "color",
        "$extensions": {
          "studio.tokens": {
            "modify": {
              "type": "darken",
              "value": "0.8",
              "space": "hsl"
            }
          }
        }
      },
      "1000": {
        "value": "{palettes.neutral.500}",
        "type": "color",
        "$extensions": {
          "studio.tokens": {
            "modify": {
              "type": "darken",
              "value": "1",
              "space": "hsl"
            }
          }
        }
      }
    }
  },
  "spacing": {
    "0": {
      "value": "0px",
      "type": "dimension"
    },
    "1": {
      "value": "0.25rem * {key-dimension.dpr}",
      "type": "dimension",
      "description": "4px @ 1dpr"
    },
    "2": {
      "value": "0.5rem * {key-dimension.dpr}",
      "type": "dimension",
      "description": "8px @ 1dpr"
    },
    "3": {
      "value": "0.75rem * {key-dimension.dpr}",
      "type": "dimension",
      "description": "12px @ 1dpr"
    },
    "4": {
      "value": "1rem * {key-dimension.dpr}",
      "type": "dimension",
      "description": "16px @ 1dpr"
    },
    "5": {
      "value": "1.25rem * {key-dimension.dpr}",
      "type": "dimension",
      "description": "20px @ 1dpr"
    },
    "6": {
      "value": "1.5rem * {key-dimension.dpr}",
      "type": "dimension",
      "description": "24px @ 1dpr"
    },
    "7": {
      "value": "1.75rem * {key-dimension.dpr}",
      "type": "dimension",
      "description": "28px @ 1dpr"
    },
    "8": {
      "value": "2rem * {key-dimension.dpr}",
      "type": "dimension",
      "description": "32px @ 1dpr"
    },
    "9": {
      "value": "2.25rem * {key-dimension.dpr}",
      "type": "dimension",
      "description": "36px @ 1dpr"
    },
    "10": {
      "value": "2.5rem * {key-dimension.dpr}",
      "type": "dimension",
      "description": "40px @ 1dpr"
    },
    "11": {
      "value": "2.75rem * {key-dimension.dpr}",
      "type": "dimension",
      "description": "44px @ 1dpr"
    },
    "12": {
      "value": "3rem * {key-dimension.dpr}",
      "type": "dimension",
      "description": "48px @ 1dpr"
    },
    "14": {
      "value": "3.5rem * {key-dimension.dpr}",
      "type": "dimension",
      "description": "56px @ 1dpr"
    },
    "16": {
      "value": "4rem * {key-dimension.dpr}",
      "type": "dimension",
      "description": "64px @ 1dpr"
    },
    "20": {
      "value": "5rem * {key-dimension.dpr}",
      "type": "dimension",
      "description": "80px @ 1dpr"
    },
    "24": {
      "value": "6rem * {key-dimension.dpr}",
      "type": "dimension",
      "description": "96px @ 1dpr"
    },
    "28": {
      "value": "7rem * {key-dimension.dpr}",
      "type": "dimension",
      "description": "112px @ 1dpr"
    },
    "32": {
      "value": "8rem * {key-dimension.dpr}",
      "type": "dimension",
      "description": "128px @ 1dpr"
    },
    "36": {
      "value": "9rem * {key-dimension.dpr}",
      "type": "dimension",
      "description": "144px @ 1dpr"
    },
    "40": {
      "value": "10rem * {key-dimension.dpr}",
      "type": "dimension",
      "description": "160px @ 1dpr"
    },
    "44": {
      "value": "11rem * {key-dimension.dpr}",
      "type": "dimension",
      "description": "176px @ 1dpr"
    },
    "48": {
      "value": "12rem * {key-dimension.dpr}",
      "type": "dimension",
      "description": "192px @ 1dpr"
    },
    "52": {
      "value": "13rem * {key-dimension.dpr}",
      "type": "dimension",
      "description": "208px @ 1dpr"
    },
    "56": {
      "value": "14rem * {key-dimension.dpr}",
      "type": "dimension",
      "description": "224px @ 1dpr"
    },
    "60": {
      "value": "15rem * {key-dimension.dpr}",
      "type": "dimension",
      "description": "240px @ 1dpr"
    },
    "64": {
      "value": "16rem * {key-dimension.dpr}",
      "type": "dimension",
      "description": "256px @ 1dpr"
    },
    "72": {
      "value": "18rem * {key-dimension.dpr}",
      "type": "dimension",
      "description": "288px @ 1dpr"
    },
    "80": {
      "value": "20rem * {key-dimension.dpr}",
      "type": "dimension",
      "description": "320px @ 1dpr"
    },
    "96": {
      "value": "24rem * {key-dimension.dpr}",
      "type": "dimension",
      "description": "384px @ 1dpr"
    },
    "0ᐧ5": {
      "value": "0.125rem * {key-dimension.dpr}",
      "type": "dimension",
      "description": "2px @ 1dpr"
    },
    "1ᐧ5": {
      "value": "0.375rem * {key-dimension.dpr}",
      "type": "dimension",
      "description": "6px @ 1dpr"
    },
    "2ᐧ5": {
      "value": "0.625rem * {key-dimension.dpr}",
      "type": "dimension",
      "description": "10px @ 1dpr"
    },
    "3ᐧ5": {
      "value": "0.825rem * {key-dimension.dpr}",
      "type": "dimension",
      "description": "13.2px @ 1dpr"
    },
    "px": {
      "value": "1px",
      "type": "dimension"
    }
  }
}