{
  "button": {
    "border-radius": {
      "value": "{border-radius.rounded}",
      "type": "borderRadius"
    },
    "label": {
      "sm": {
        "value": "{font-size.text-sm}",
        "type": "typography"
      },
      "md": {
        "value": "{font-size.text-sm}",
        "type": "typography"
      },
      "lg": {
        "value": "{font-size.text-base}",
        "type": "typography"
      }
    },
    "filled": {
      "default": {
        "value": "{primary.default}",
        "type": "color"
      },
      "hover": {
        "value": "{primary.tint-low}",
        "type": "color"
      },
      "pressed": {
        "value": "{primary.tint-medium}",
        "type": "color"
      },
      "focus": {
        "value": "{primary.tint-low}",
        "type": "color"
      },
      "disabled": {
        "value": "{palettes.neutral.200}",
        "type": "color"
      }
    },
    "on-filled": {
      "default": {
        "value": "{on-primary.default}",
        "type": "color"
      },
      "disabled": {
        "value": "{palettes.neutral.400}",
        "type": "color"
      }
    },
    "focus-ring": {
      "value": {
        "color": "{primary.outline}",
        "width": "3"
      },
      "type": "border"
    },
    "outlined": {
      "default": {
        "value": "{on-primary.default}",
        "type": "color"
      },
      "hover": {
        "value": "{on-primary.tint-low}",
        "type": "color"
      },
      "pressed": {
        "value": "{on-primary.tint-medium}",
        "type": "color"
      },
      "focus": {
        "value": "{on-primary.tint-low}",
        "type": "color"
      },
      "disabled": {
        "value": "{palettes.neutral.50}",
        "type": "color"
      }
    },
    "on-outlined": {
      "default": {
        "value": "{primary.default}",
        "type": "color"
      },
      "disabled": {
        "value": "{palettes.neutral.200}",
        "type": "color"
      }
    },
    "tonal": {
      "default": {
        "value": "{primary-container.default}",
        "type": "color"
      },
      "hover": {
        "value": "{primary-container.tint-low}",
        "type": "color"
      },
      "pressed": {
        "value": "{primary-container.tint-medium}",
        "type": "color"
      },
      "focus": {
        "value": "{primary-container.tint-low}",
        "type": "color"
      },
      "disabled": {
        "value": "{palettes.neutral.100}",
        "type": "color"
      }
    },
    "on-tonal": {
      "default": {
        "value": "{on-primary-container.default}",
        "type": "color"
      },
      "disabled": {
        "value": "{palettes.neutral.200}",
        "type": "color"
      }
    },
    "text": {
      "default": {
        "value": "{on-primary.default}",
        "type": "color",
        "$extensions": {
          "studio.tokens": {
            "modify": {
              "type": "alpha",
              "value": "0",
              "space": "lch"
            }
          }
        }
      },
      "hover": {
        "value": "{on-primary.tint-low}",
        "type": "color"
      },
      "pressed": {
        "value": "{on-primary.tint-medium}",
        "type": "color"
      },
      "focus": {
        "value": "{on-primary.tint-low}",
        "type": "color"
      },
      "disabled": {
        "value": "{palettes.neutral.50}",
        "type": "color",
        "$extensions": {
          "studio.tokens": {
            "modify": {
              "type": "alpha",
              "value": "0",
              "space": "lch"
            }
          }
        }
      }
    },
    "on-text": {
      "default": {
        "value": "{primary.default}",
        "type": "color"
      },
      "disabled": {
        "value": "{palettes.neutral.200}",
        "type": "color"
      }
    }
  },
  "text-input": {
    "sm": {
      "px": {
        "value": "{padding.px-4}",
        "type": "spacing",
        "description": "x-padding for small buttons"
      },
      "py": {
        "value": "{padding.px-2}",
        "type": "spacing",
        "description": "y-padding for small buttons"
      },
      "item-spacing": {
        "value": "{spacing.2}",
        "type": "spacing",
        "description": "spacing between items"
      }
    },
    "md": {
      "pl": {
        "value": "{padding.px-4}",
        "type": "spacing",
        "description": "Padding-left"
      },
      "pr": {
        "value": "{padding.px-2ᐧ5}",
        "type": "spacing",
        "description": "Padding-right"
      },
      "py": {
        "value": "{padding.px-2ᐧ5}",
        "type": "spacing",
        "description": "y-padding for medium buttons"
      },
      "item-spacing": {
        "value": "{spacing.2}",
        "type": "spacing",
        "description": "spacing between items"
      }
    },
    "lg": {
      "px": {
        "value": "{padding.px-5}",
        "type": "spacing",
        "description": "x-padding for large buttons"
      },
      "py": {
        "value": "{padding.px-3}",
        "type": "spacing",
        "description": "y-padding for large buttons"
      },
      "item-spacing": {
        "value": "{spacing.2}",
        "type": "spacing"
      }
    }
  }
}